integry/__init__.py
integry/client.py
integry/exceptions.py
integry/resources/base.py
integry/resources/apps/api.py
integry/resources/apps/types.py
integry/resources/functions/api.py
integry/resources/functions/types.py
integry/tool_handlers/lite_llm.py
integry/tool_handlers/mistralai.py
integry/utils/__init__.py
integry/utils/common.py
integry/utils/pydantic.py
integry-0.0.13.dist-info/METADATA
integry-0.0.13.dist-info/WHEEL
integry-0.0.13.dist-info/licenses/LICENSE
integry-0.0.13.dist-info/RECORD
