Metadata-Version: 2.4
Name: integry
Version: 0.0.13
Summary: The official Python library for the Integry API
Project-URL: Homepage, https://github.com/IntegryHQ/integry
Project-URL: Issues, https://github.com/IntegryHQ/integry/issues
Author-email: Integry <hello@integry.io>
License-File: LICENSE
Classifier: Intended Audience :: Developers
Classifier: License :: OSI Approved :: Apache Software License
Classifier: Operating System :: OS Independent
Classifier: Programming Language :: Python :: 3.12
Classifier: Typing :: Typed
Requires-Python: >=3.12
Requires-Dist: httpx<1,>=0.27.0
Requires-Dist: pydantic<3,>=2.9.0
